adeft/__init__.py
adeft/disambiguate.py
adeft/discover.py
adeft/locations.py
adeft/nlp.py
adeft/recognize.py
adeft/util.py
adeft/download/__init__.py
adeft/download/__main__.py
adeft/download/download.py
adeft/gui/__init__.py
adeft/gui/ground/__init__.py
adeft/gui/ground/ground.py
adeft/modeling/__init__.py
adeft/modeling/classify.py
adeft/modeling/label.py
adeft-0.4.0.dist-info/LICENSE
adeft-0.4.0.dist-info/METADATA
adeft-0.4.0.dist-info/WHEEL
adeft-0.4.0.dist-info/top_level.txt
adeft-0.4.0.dist-info/RECORD
