Metadata-Version: 2.1
Name: adeft
Version: 0.4.0
Summary: Acromine based Disambiguation of Entities From Text
Home-page: https://github.com/indralab/adeft
Author: adeft developers, Harvard Medical School
Author-email: albert_steppi@hms.harvard.edu
License: UNKNOWN
Download-URL: https://github.com/indralab/adeft/archive/0.4.0.tar.gz
Keywords: nlp,biology,disambiguation
Platform: UNKNOWN
Classifier: Development Status :: 4 - Beta
Classifier: Programming Language :: Python :: 3.5
Classifier: Programming Language :: Python :: 3.6
Classifier: Programming Language :: Python :: 3.7
Requires-Dist: nltk
Requires-Dist: scikit-learn (>=0.20.0)
Requires-Dist: wget
Requires-Dist: requests
Requires-Dist: flask
Provides-Extra: test
Requires-Dist: nose ; extra == 'test'
Requires-Dist: coverage ; extra == 'test'
